MANIFEST.in
README.rst
setup.cfg
setup.py
docs/HISTORY.rst
docs/INSTALL.rst
docs/LICENSE.GPL
docs/LICENSE.txt
plonegovmy/__init__.py
plonegovmy.policy.egg-info/PKG-INFO
plonegovmy.policy.egg-info/SOURCES.txt
plonegovmy.policy.egg-info/dependency_links.txt
plonegovmy.policy.egg-info/entry_points.txt
plonegovmy.policy.egg-info/namespace_packages.txt
plonegovmy.policy.egg-info/not-zip-safe
plonegovmy.policy.egg-info/paster_plugins.txt
plonegovmy.policy.egg-info/requires.txt
plonegovmy.policy.egg-info/top_level.txt
plonegovmy/policy/__init__.py
plonegovmy/policy/configure.zcml
plonegovmy/policy/interfaces.py
plonegovmy/policy/setuphandlers.py
plonegovmy/policy/locales/README.txt
plonegovmy/policy/profiles/default/browserlayer.xml
plonegovmy/policy/profiles/default/metadata.xml
plonegovmy/policy/profiles/default/plonegovmy.policy.marker.txt
plonegovmy/policy/upgrades/__init__.py
plonegovmy/policy/upgrades/handlers.py
plonegovmy/policy/upgrades/profiles.py