Metadata-Version: 1.1
Name: plonegovmy.policy
Version: 1.0b1
Summary: UNKNOWN
Home-page: http://github.com/plonegovmy/
Author: Inigo Consulting
Author-email: team@inigo-tech.com
License: gpl
Platform: UNKNOWN
Classifier: Framework :: Plone
Classifier: Programming Language :: Python
Classifier: Topic :: Software Development :: Libraries :: Python Modules
